Workbook

Sheet Problems
A1: Problem # | B1: Difficulty | C1: Company | D1: Title | E1: Description | F1: Status | G1: Python | H1: JavaScript | I1: TypeScript | J1: Rust | K1: C++ | L1: C | M1: Java | N1: Bash | O1: # Languages
A2: 2 | B2: Hard | C2: Uber | D2: Given an array of integers, return a new array such that each element at index i of the new array is... | E2: Given an array of integers, return a new array such that each element at index i of the new array is the product of all the numbers in the original array except the one at i. For example, if our input was [1, 2, 3, 4, 5], the expected output would be [120, 60, 40, 30, 24]. If our input was [3, 2, 1], the expected output would be [2, 3, 6]. Follow-up: what if you can't use division? | F2: Not Started | O2: =COUNTA(G2:N2) -> 0
A3: 3 | B3: Medium | C3: Google | D3: Given the root to a binary tree, implement serialize(root), which serializes the tree into a string,... | E3: Given the root to a binary tree, implement serialize(root), which serializes the tree into a string, and deserialize(s), which deserializes the string back into the tree. For example, given the following Node class class Node: def __init__(self, val, left=None, right=None): self.val = val self.left = left self.right = right The following test should pass: node = Node('root', Node('left', Node('left.left')), Node('right')) assert deserialize(serialize(node)).left.left.val == 'left.left' | F3: Not Started | O3: =COUNTA(G3:N3) -> 0
A4: 4 | B4: Hard | C4: Stripe | D4: Given an array of integers, find the first missing positive integer in linear time and constant spac... | E4: Given an array of integers, find the first missing positive integer in linear time and constant space. In other words, find the lowest positive integer that does not exist in the array. The array can contain duplicates and negative numbers as well. For example, the input [3, 4, -1, 1] should give 2. The input [1, 2, 0] should give 3. You can modify the input array in-place. | F4: Not Started | O4: =COUNTA(G4:N4) -> 0
A5: 5 | B5: Medium | C5: Jane Street | D5: cons(a, b) constructs a pair, and car(pair) and cdr(pair) returns the first and last element of that... | E5: cons(a, b) constructs a pair, and car(pair) and cdr(pair) returns the first and last element of that pair. For example, car(cons(3, 4)) returns 3, and cdr(cons(3, 4)) returns 4. Given this implementation of cons: def cons(a, b): def pair(f): return f(a, b) return pair Implement car and cdr. | F5: Not Started | O5: =COUNTA(G5:N5) -> 0
A6: 6 | B6: Hard | C6: Google | D6: An XOR linked list is a more memory efficient doubly linked list. | E6: An XOR linked list is a more memory efficient doubly linked list. Instead of each node holding next and prev fields, it holds a field named both, which is an XOR of the next node and the previous node. Implement an XOR linked list; it has an add(element) which adds the element to the end, and a get(index) which returns the node at index. If using a language that has no pointers (such as Python), you can assume you have access to get_pointer anddereference_pointer functions that converts between nodes and memory addresses. | F6: Not Started | O6: =COUNTA(G6:N6) -> 0
A7: 7 | B7: Medium | C7: Facebook | D7: Given the mapping a = 1, b = 2, . | E7: Given the mapping a = 1, b = 2, ... z = 26, and an encoded message, count the number of ways it can be decoded. For example, the message '111' would give 3, since it could be decoded as 'aaa', 'ka', and 'ak'. You can assume that the messages are decodable. For example, '001' is not allowed. | F7: Not Started | O7: =COUNTA(G7:N7) -> 0
A8: 8 | B8: Easy | C8: Google | D8: A unival tree (which stands for "universal value") is a tree where all nodes under it have the same ... | E8: A unival tree (which stands for "universal value") is a tree where all nodes under it have the same value. Given the root to a binary tree, count the number of unival subtrees. For example, the following tree has 5 unival subtrees: 0 / \ 1 0 / \ 1 0 / \ 1 1 | F8: Solved | J8: 45663 | M8: 46028 | O8: =COUNTA(G8:N8) -> 2
A9: 9 | B9: Hard | C9: Airbnb | D9: Given a list of integers, write a function that returns the largest sum of non-adjacent numbers. | E9: Given a list of integers, write a function that returns the largest sum of non-adjacent numbers. Numbers can be 0 or negative. For example, [2, 4, 6, 2, 5] should return 13, since we pick 2, 6, and 5. [5, 1, 1, 5] should return 10, since we pick 5 and 5. Follow-up: Can you do this in O(N) time and constant space? | F9: Not Started | O9: =COUNTA(G9:N9) -> 0
A10: 10 | B10: Medium | C10: Apple | D10: Implement a job scheduler which takes in a function f and an integer n, and calls f after n millisec... | E10: Implement a job scheduler which takes in a function f and an integer n, and calls f after n milliseconds. | F10: Not Started | O10: =COUNTA(G10:N10) -> 0
A11: 11 | B11: Medium | C11: Twitter | D11: Implement an autocomplete system. | E11: Implement an autocomplete system. That is, given a query string s and a set of all possible query strings, return all strings in the set that have s as a prefix. For example, given the query string de and the set of strings [dog, deer, deal], return [deer, deal]. Hint: Try preprocessing the dictionary into a more efficient data structure to speed up queries. | F11: Not Started | O11: =COUNTA(G11:N11) -> 0
A12: 12 | B12: Hard | C12: Amazon | D12: There exists a staircase with N steps, and you can climb up either 1 or 2 steps at a time. | E12: There exists a staircase with N steps, and you can climb up either 1 or 2 steps at a time. Given N, write a function that returns the number of unique ways you can climb the staircase. The order of the steps matters. For example, if N is 4, then there are 5 unique ways: * 1, 1, 1, 1 * 2, 1, 1 * 1, 2, 1 * 1, 1, 2 * 2, 2 What if, instead of being able to climb 1 or 2 steps at a time, you could climb any number from a set of positive integers X? For example, if X = {1, 3, 5}, you could climb 1, 3, or 5 steps at a time. | F12: Not Started | O12: =COUNTA(G12:N12) -> 0
A13: 13 | B13: Hard | C13: Amazon | D13: Given an integer k and a string s, find the length of the longest substring that contains at most k ... | E13: Given an integer k and a string s, find the length of the longest substring that contains at most k distinct characters. For example, given s = "abcba" and k = 2, the longest substring with k distinct characters is "bcb". | F13: Not Started | O13: =COUNTA(G13:N13) -> 0
A14: 14 | B14: Medium | C14: Google | D14: The area of a circle is defined as πr^2. | E14: The area of a circle is defined as πr^2. Estimate π to 3 decimal places using a Monte Carlo method. Hint: The basic equation of a circle is x2 + y2 = r2. | F14: Not Started | O14: =COUNTA(G14:N14) -> 0
A15: 15 | B15: Medium | C15: Facebook | D15: Given a stream of elements too large to store in memory, pick a random element from the stream with ... | E15: Given a stream of elements too large to store in memory, pick a random element from the stream with uniform probability. | F15: Not Started | O15: =COUNTA(G15:N15) -> 0
A16: 16 | B16: Easy | C16: Twitter | D16: You run an e-commerce website and want to record the last N order ids in a log. | E16: You run an e-commerce website and want to record the last N order ids in a log. Implement a data structure to accomplish this, with the following API: * record(order_id): adds the order_id to the log * get_last(i): gets the ith last element from the log. i is guaranteed to be smaller than or equal to N. You should be as efficient with time and space as possible. | F16: Not Started | O16: =COUNTA(G16:N16) -> 0
A17: 17 | B17: Hard | C17: Google | D17: Suppose we represent our file system by a string in the following manner: The string "dir\n\tsubdir1... | E17: Suppose we represent our file system by a string in the following manner: The string "dir\n\tsubdir1\n\tsubdir2\n\t\tfile.ext" represents: dir subdir1 subdir2 file.ext The directory dir contains an empty sub-directory subdir1 and a sub-directory subdir2 containing a file file.ext. The string "dir\n\tsubdir1\n\t\tfile1.ext\n\t\tsubsubdir1\n\tsubdir2\n\t\tsubsubdir2\n\t\t\tfile2.ext" represents: dir subdir1 file1.ext subsubdir1 subdir2 subsubdir2 file2.ext The directory dir contains two sub-directories subdir1 and subdir2. subdir1 contains a file file1.extand an empty second-level sub-directory subsubdir1. subdir2 contains a second-level sub-directorysubsubdir2 containing a file file2.ext. We are interested in finding the longest (number of characters) absolute path to a file within our file system. For example, in the second example above, the longest absolute path is "dir/subdir2/subsubdir2/file2.ext", and its length is 32 (not including the double quotes). Given a string representing | F17: Not Started | O17: =COUNTA(G17:N17) -> 0
A18: 18 | B18: Hard | C18: Google | D18: Given an array of integers and a number k, where 1 <= k <= length of the array, compute the maximum ... | E18: Given an array of integers and a number k, where 1 <= k <= length of the array, compute the maximum values of each subarray of length k. For example, given array = [10, 5, 2, 7, 8, 7] and k = 3, we should get: [10, 7, 8, 8], since: * 10 = max(10, 5, 2) * 7 = max(5, 2, 7) * 8 = max(2, 7, 8) * 8 = max(7, 8, 7) Do this in O(n) time and O(k) space. You can modify the input array in-place and you do not need to store the results. You can simply print them out as you compute them. | F18: Not Started | O18: =COUNTA(G18:N18) -> 0
A19: 19 | B19: Medium | C19: Facebook | D19: A builder is looking to build a row of N houses that can be of K different colors. | E19: A builder is looking to build a row of N houses that can be of K different colors. He has a goal of minimizing cost while ensuring that no two neighboring houses are of the same color. Given an N by K matrix where the nth row and kth column represents the cost to build the nthhouse with kth color, return the minimum cost which achieves this goal. | F19: Not Started | O19: =COUNTA(G19:N19) -> 0
A20: 20 | B20: Easy | C20: Google | D20: Given two singly linked lists that intersect at some point, find the intersecting node. | E20: Given two singly linked lists that intersect at some point, find the intersecting node. The lists are non-cyclical. For example, given A = 3 -> 7 -> 8 -> 10 and B = 99 -> 1 -> 8 -> 10, return the node with value 8. In this example, assume nodes with the same value are the exact same node objects. Do this in O(M + N) time (where M and N are the lengths of the lists) and constant space. | F20: Not Started | O20: =COUNTA(G20:N20) -> 0
... A26: 26 | B26: Medium | C26: Google | D26: Given a singly linked list and an integer k, remove the kth last element from the list. | E26: Given a singly linked list and an integer k, remove the kth last element from the list. k is guaranteed to be smaller than the length of the list. The list is very long, so making more than one pass is prohibitively expensive. Do this in constant space and in one pass. | F26: Not Started | O26: =COUNTA(G26:N26) -> 0
A27: 27 | B27: Easy | C27: Facebook | D27: Given a string of round, curly, and square open and closing brackets, return whether the brackets ar... | E27: Given a string of round, curly, and square open and closing brackets, return whether the brackets are balanced (well-formed). For example, given the string "([])[]({})", you should return true. Given the string "([)]" or "((()", you should return false. | F27: Solved | G27: 46026 | H27: 46028 | J27: 46023 | O27: =COUNTA(G27:N27) -> 3
A28: 28 | B28: Medium | C28: Palantir | D28: Write an algorithm to justify text. | E28: Write an algorithm to justify text. Given a sequence of words and an integer line length k, return a list of strings which represents each line, fully justified. More specifically, you should have as many words as possible in each line. There should be at least one space between each word. Pad extra spaces when necessary so that each line has exactly length k. Spaces should be distributed as equally as possible, with the extra spaces, if any, distributed starting from the left. If you can only fit one word on a line, then you should pad the right-hand side with spaces. Each word is guaranteed not to be longer than k. For example, given the list of words ["the", "quick", "brown", "fox", "jumps", "over", "the", "lazy", "dog"] and k = 16, you should return the following: ["the quick brown", # 1 extra space on the left "fox jumps over", # 2 extra spaces distributed evenly "the lazy dog"] # 4 extra spaces distributed evenly | F28: Not Started | O28: =COUNTA(G28:N28) -> 0
A29: 29 | B29: Easy | C29: Amazon | D29: Run-length encoding is a fast and simple method of encoding strings. | E29: Run-length encoding is a fast and simple method of encoding strings. The basic idea is to represent repeated successive characters as a single count and character. For example, the string "AAAABBBCCDAA" would be encoded as "4A3B2C1D2A". Implement run-length encoding and decoding. You can assume the string to be encoded have no digits and consists solely of alphabetic characters. You can assume the string to be decoded is valid. | F29: Solved | J29: 46030 | O29: =COUNTA(G29:N29) -> 1
A30: 30 | B30: Medium | C30: Facebook | D30: You are given an array of non-negative integers that represents a two-dimensional elevation map wher... | E30: You are given an array of non-negative integers that represents a two-dimensional elevation map where each element is unit-width wall and the integer is the height. Suppose it will rain and all spots between two walls get filled up. Compute how many units of water remain trapped on the map in O(N) time and O(1) space. For example, given the input [2, 1, 2], we can hold 1 unit of water in the middle. Given the input [3, 0, 1, 3, 0, 5], we can hold 3 units in the first index, 2 in the second, and 3 in the fourth index (we cannot hold 5 since it would run off to the left), so we can trap 8 units of water. | F30: Not Started | O30: =COUNTA(G30:N30) -> 0
A31: 31 | B31: Easy | C31: Google | D31: The edit distance between two strings refers to the minimum number of character insertions, deletion... | E31: The edit distance between two strings refers to the minimum number of character insertions, deletions, and substitutions required to change one string to the other. For example, the edit distance between “kitten” and “sitting” is three: substitute the “k” for “s”, substitute the “e” for “i”, and append a “g”. Given two strings, compute the edit distance between them. | F31: Not Started | O31: =COUNTA(G31:N31) -> 0
A32: 32 | B32: Hard | C32: Jane Street | D32: Suppose you are given a table of currency exchange rates, represented as a 2D array. | E32: Suppose you are given a table of currency exchange rates, represented as a 2D array. Determine whether there is a possible arbitrage: that is, whether there is some sequence of trades you can make, starting with some amount A of any currency, so that you can end up with some amount greater than A of that currency. There are no transaction costs and you can trade fractional quantities. | F32: Not Started | O32: =COUNTA(G32:N32) -> 0
A33: 33 | B33: Easy | C33: Microsoft | D33: Compute the running median of a sequence of numbers. | E33: Compute the running median of a sequence of numbers. That is, given a stream of numbers, print out the median of the list so far on each new element. Recall that the median of an even-numbered list is the average of the two middle numbers. For example, given the sequence [2, 1, 5, 7, 2, 0, 5], your algorithm should print out: 2 1.5 2 3.5 2 2 2 | F33: Not Started | O33: =COUNTA(G33:N33) -> 0
A34: 34 | B34: Medium | C34: Quora | D34: Given a string, find the palindrome that can be made by inserting the fewest number of characters as... | E34: Given a string, find the palindrome that can be made by inserting the fewest number of characters as possible anywhere in the word. If there is more than one palindrome of minimum length that can be made, return the lexicographically earliest one (the first one alphabetically). For example, given the string "race", you should return "ecarace", since we can add three letters to it (which is the smallest amount to make a palindrome). There are seven other palindromes that can be made from "race" by adding three letters, but "ecarace" comes first alphabetically. As another example, given the string "google", you should return "elgoogle". | F34: Not Started | O34: =COUNTA(G34:N34) -> 0
A35: 35 | B35: Hard | C35: Google | D35: Given an array of strictly the characters 'R', 'G', and 'B', segregate the values of the array so th... | E35: Given an array of strictly the characters 'R', 'G', and 'B', segregate the values of the array so that all the Rs come first, the Gs come second, and the Bs come last. You can only swap elements of the array. Do this in linear time and in-place. For example, given the array ['G', 'B', 'R', 'R', 'B', 'R', 'G'], it should become ['R', 'R', 'R', 'G', 'G', 'B', 'B']. | F35: Not Started | O35: =COUNTA(G35:N35) -> 0
A36: 36 | B36: Medium | C36: Dropbox | D36: Given the root to a binary search tree, find the second largest node in the tree. | E36: Given the root to a binary search tree, find the second largest node in the tree. | F36: Not Started | O36: =COUNTA(G36:N36) -> 0
A37: 37 | B37: Easy | C37: Google | D37: The power set of a set is the set of all its subsets. | E37: The power set of a set is the set of all its subsets. Write a function that, given a set, generates its power set. For example, given the set {1, 2, 3}, it should return {{}, {1}, {2}, {3}, {1, 2}, {1, 3}, {2, 3}, {1, 2, 3}}. You may also use a list or array to represent a set. | F37: Not Started | O37: =COUNTA(G37:N37) -> 0
A38: 38 | B38: Hard | C38: Microsoft | D38: You have an N by N board. | E38: You have an N by N board. Write a function that, given N, returns the number of possible arrangements of the board where N queens can be placed on the board without threatening each other, i.e. no two queens share the same row, column, or diagonal. | F38: Not Started | O38: =COUNTA(G38:N38) -> 0
A39: 39 | B39: Medium | C39: Dropbox | D39: Conway's Game of Life takes place on an infinite two-dimensional board of square cells. | E39: Conway's Game of Life takes place on an infinite two-dimensional board of square cells. Each cell is either dead or alive, and at each tick, the following rules apply: * Any live cell with less than two live neighbours dies. * Any live cell with two or three live neighbours remains living. * Any live cell with more than three live neighbours dies. * Any dead cell with exactly three live neighbours becomes a live cell. A cell neighbours another cell if it is horizontally, vertically, or diagonally adjacent. Implement Conway's Game of Life. It should be able to be initialized with a starting list of live cell coordinates and the number of steps it should run for. Once initialized, it should print out the board state at each step. Since it's an infinite board, print out only the relevant coordinates, i.e. from the top-leftmost live cell to bottom-rightmost live cell. You can represent a live cell with an asterisk (*) and a dead cell with a dot (. ). | F39: Not Started | O39: =COUNTA(G39:N39) -> 0
A40: 40 | B40: Hard | C40: Google | D40: Given an array of integers where every integer occurs three times except for one integer, which only... | E40: Given an array of integers where every integer occurs three times except for one integer, which only occurs once, find and return the non-duplicated integer. For example, given [6, 1, 3, 3, 3, 6, 6], return 1. Given [13, 19, 13, 13], return 19. Do this in O(N) time and O(1) space. | F40: Not Started | O40: =COUNTA(G40:N40) -> 0
A41: 41 | B41: Medium | C41: Facebook | D41: Given an unordered list of flights taken by someone, each represented as (origin, destination) pairs... | E41: Given an unordered list of flights taken by someone, each represented as (origin, destination) pairs, and a starting airport, compute the person's itinerary. If no such itinerary exists, return null. If there are multiple possible itineraries, return the lexicographically smallest one. All flights must be used in the itinerary. For example, given the list of flights [('SFO', 'HKO'), ('YYZ', 'SFO'), ('YUL', 'YYZ'), ('HKO', 'ORD')] and starting airport 'YUL', you should return the list ['YUL', 'YYZ', 'SFO', 'HKO', 'ORD']. Given the list of flights [('SFO', 'COM'), ('COM', 'YYZ')] and starting airport 'COM', you should return null. Given the list of flights [('A', 'B'), ('A', 'C'), ('B', 'C'), ('C', 'A')] and starting airport 'A', you should return the list ['A', 'B', 'C', 'A', 'C'] even though ['A', 'C', 'A', 'B', 'C'] is also a valid itinerary. However, the first one is lexicographically smaller. | F41: Not Started | O41: =COUNTA(G41:N41) -> 0
A42: 42 | B42: Hard | C42: Google | D42: Given a list of integers S and a target number k, write a function that returns a subset of S that a... | E42: Given a list of integers S and a target number k, write a function that returns a subset of S that adds up to k. If such a subset cannot be made, then return null. Integers can appear more than once in the list. You may assume all numbers in the list are positive. For example, given S = [12, 1, 61, 5, 9, 2] and k = 24, return [12, 9, 2, 1] since it sums up to 24. | F42: Not Started | O42: =COUNTA(G42:N42) -> 0
A43: 43 | B43: Easy | C43: Amazon | D43: Implement a stack that has the following methods: * push(val), which pushes an element onto the stac... | E43: Implement a stack that has the following methods: * push(val), which pushes an element onto the stack * pop(), which pops off and returns the topmost element of the stack. If there are no elements in the stack, then it should throw an error or return null. * max(), which returns the maximum value in the stack currently. If there are no elements in the stack, then it should throw an error or return null. Each method should run in constant time. | F43: Solved | J43: 46025 | O43: =COUNTA(G43:N43) -> 1
A44: 44 | B44: Medium | C44: Google | D44: We can determine how "out of order" an array A is by counting the number of inversions it has. | E44: We can determine how "out of order" an array A is by counting the number of inversions it has. Two elements A[i] and A[j] form an inversion if A[i] > A[j] but i < j. That is, a smaller element appears after a larger element. Given an array, count the number of inversions it has. Do this faster than O(N^2) time. You may assume each element in the array is distinct. For example, a sorted list has zero inversions. The array [2, 4, 1, 3, 5] has three inversions: (2, 1), (4, 1), and (4, 3). The array [5, 4, 3, 2, 1] has ten inversions: every distinct pair forms an inversion. | F44: Not Started | O44: =COUNTA(G44:N44) -> 0
A45: 45 | B45: Easy | C45: Two Sigma | D45: Using a function rand5() that returns an integer from 1 to 5 (inclusive) with uniform probability, i... | E45: Using a function rand5() that returns an integer from 1 to 5 (inclusive) with uniform probability, implement a function rand7() that returns an integer from 1 to 7 (inclusive). | F45: Not Started | O45: =COUNTA(G45:N45) -> 0
A46: 46 | B46: Hard | C46: Amazon | D46: Given a string, find the longest palindromic contiguous substring. | E46: Given a string, find the longest palindromic contiguous substring. If there are more than one with the maximum length, return any one. For example, the longest palindromic substring of "aabcdcb" is "bcdcb". The longest palindromic substring of "bananas" is "anana". | F46: Not Started | O46: =COUNTA(G46:N46) -> 0
A47: 47 | B47: Easy | C47: Facebook | D47: Given a array of numbers representing the stock prices of a company in chronological order, write a ... | E47: Given a array of numbers representing the stock prices of a company in chronological order, write a function that calculates the maximum profit you could have made from buying and selling that stock once. You must buy before you can sell it. For example, given [9, 11, 8, 5, 7, 10], you should return 5, since you could buy the stock at 5 dollars and sell it at 10 dollars. | F47: Solved | G47: 46029 | J47: 46029 | O47: =COUNTA(G47:N47) -> 2
A48: 48 | B48: Medium | C48: Google | D48: Given pre-order and in-order traversals of a binary tree, write a function to reconstruct the tree. | E48: Given pre-order and in-order traversals of a binary tree, write a function to reconstruct the tree. For example, given the following preorder traversal: [a, b, d, e, c, f, g] And the following inorder traversal: [d, b, e, a, f, c, g] You should return the following tree: a / \ b c / \ / \ d e f g | F48: Not Started | O48: =COUNTA(G48:N48) -> 0
A49: 49 | B49: Medium | C49: Amazon | D49: Given an array of numbers, find the maximum sum of any contiguous subarray of the array. | E49: Given an array of numbers, find the maximum sum of any contiguous subarray of the array. For example, given the array [34, -50, 42, 14, -5, 86], the maximum sum would be 137, since we would take elements 42, 14, -5, and 86. Given the array [-5, -1, -8, -9], the maximum sum would be 0, since we would not take any elements. Do this in O(N) time. | F49: Solved | G49: 45661 | J49: 46026 | O49: =COUNTA(G49:N49) -> 2
A50: 50 | B50: Easy | C50: Microsoft | D50: Suppose an arithmetic expression is given as a binary tree. | E50: Suppose an arithmetic expression is given as a binary tree. Each leaf is an integer and each internal node is one of '+', '−', '∗', or '/'. Given the root to such a tree, write a function to evaluate it. For example, given the following tree: * / \ + + / \ / \ 3 2 4 5 You should return 45, as it is (3 + 2) * (4 + 5). | F50: Not Started | O50: =COUNTA(G50:N50) -> 0
A51: 51 | B51: Medium | C51: Facebook | D51: Given a function that generates perfectly random numbers between 1 and k (inclusive), where k is an ... | E51: Given a function that generates perfectly random numbers between 1 and k (inclusive), where k is an input, write a function that shuffles a deck of cards represented as an array using only swaps. It should run in O(N) time. Hint: Make sure each one of the 52! permutations of the deck is equally likely. | F51: Not Started | O51: =COUNTA(G51:N51) -> 0
A52: 52 | B52: Hard | C52: Google | D52: Implement an LRU (Least Recently Used) cache. | E52: Implement an LRU (Least Recently Used) cache. It should be able to be initialized with a cache size n, and contain the following methods: * set(key, value): sets key to value. If there are already n items in the cache and we are adding a new item, then it should also remove the least recently used item. * get(key): gets the value at key. If no such key exists, return null. Each operation should run in O(1) time. | F52: Not Started | O52: =COUNTA(G52:N52) -> 0
A53: 53 | B53: Medium | C53: Apple | D53: Implement a queue using two stacks. | E53: Implement a queue using two stacks. Recall that a queue is a FIFO (first-in, first-out) data structure with the following methods: enqueue, which inserts an element into the queue, and dequeue, which removes it. | F53: Not Started | O53: =COUNTA(G53:N53) -> 0
A54: 54 | B54: Hard | C54: Dropbox | D54: Sudoku is a puzzle where you're given a partially-filled 9 by 9 grid with digits. | E54: Sudoku is a puzzle where you're given a partially-filled 9 by 9 grid with digits. The objective is to fill the grid with the constraint that every row, column, and box (3 by 3 subgrid) must contain all of the digits from 1 to 9. Implement an efficient sudoku solver. | F54: Not Started | O54: =COUNTA(G54:N54) -> 0
A55: 55 | B55: Easy | C55: Microsoft | D55: Implement a URL shortener with the following methods: * shorten(url), which shortens the url into a ... | E55: Implement a URL shortener with the following methods: * shorten(url), which shortens the url into a six-character alphanumeric string, such as zLg6wl. * restore(short), which expands the shortened string into the original url. If no such shortened string exists, return null. Hint: What if we enter the same URL twice? | F55: Not Started | O55: =COUNTA(G55:N55) -> 0
A56: 56 | B56: Medium | C56: Google | D56: Given an undirected graph represented as an adjacency matrix and an integer k, write a function to d... | E56: Given an undirected graph represented as an adjacency matrix and an integer k, write a function to determine whether each vertex in the graph can be colored such that no two adjacent vertices share the same color using at most k colors. | F56: Not Started | O56: =COUNTA(G56:N56) -> 0
A57: 57 | B57: Medium | C57: Amazon | D57: Given a string s and an integer k, break up the string into multiple lines such that each line has a... | E57: Given a string s and an integer k, break up the string into multiple lines such that each line has a length of k or less. You must break it up so that words don't break across lines. Each line has to have the maximum possible amount of words. If there's no way to break the text up, then return null. You can assume that there are no spaces at the ends of the string and that there is exactly one space between each word. For example, given the string "the quick brown fox jumps over the lazy dog" and k = 10, you should return: ["the quick", "brown fox", "jumps over", "the lazy", "dog"]. No string in the list has a length of more than 10. | F57: Not Started | O57: =COUNTA(G57:N57) -> 0
A58: 58 | B58: Medium | C58: Amazon | D58: An sorted array of integers was rotated an unknown number of times. | E58: An sorted array of integers was rotated an unknown number of times. Given such an array, find the index of the element in the array in faster than linear time. If the element doesn't exist in the array, return null. For example, given the array [13, 18, 25, 2, 8, 10] and the element 8, return 4 (the index of 8 in the array). You can assume all the integers in the array are unique. | F58: Not Started | O58: =COUNTA(G58:N58) -> 0
A59: 59 | B59: Hard | C59: Google | D59: Implement a file syncing algorithm for two computers over a low-bandwidth network. | E59: Implement a file syncing algorithm for two computers over a low-bandwidth network. What if we know the files in the two computers are mostly the same? | F59: Not Started | O59: =COUNTA(G59:N59) -> 0
A60: 60 | B60: Medium | C60: Facebook | D60: Given a multiset of integers, return whether it can be partitioned into two subsets whose sums are t... | E60: Given a multiset of integers, return whether it can be partitioned into two subsets whose sums are the same. For example, given the multiset {15, 5, 20, 10, 35, 15, 10}, it would return true, since we can split it up into {15, 5, 10, 15, 10} and {20, 35}, which both add up to 55. Given the multiset {15, 5, 20, 10, 35}, it would return false, since we can't split it up into two subsets that add up to the same sum. | F60: Not Started | O60: =COUNTA(G60:N60) -> 0
A61: 61 | B61: Medium | C61: Google | D61: Implement integer exponentiation. | E61: Implement integer exponentiation. That is, implement the pow(x, y) function, where x and y are integers and returns x^y. Do this faster than the naive method of repeated multiplication. For example, pow(2, 10) should return 1024. | F61: Not Started | O61: =COUNTA(G61:N61) -> 0
... A68: 68 | B68: Medium | C68: Google | D68: On our special chessboard, two bishops attack each other if they share the same diagonal. | E68: On our special chessboard, two bishops attack each other if they share the same diagonal. This includes bishops that have another bishop located between them, i.e. bishops can attack through pieces. You are given N bishops, represented as (row, column) tuples on a M by M chessboard. Write a function to count the number of pairs of bishops that attack each other. The ordering of the pair doesn't matter: (1, 2) is considered the same as (2, 1). For example, given M = 5 and the list of bishops: * (0, 0) * (1, 2) * (2, 2) * (4, 0) The board would look like this: [b 0 0 0 0] [0 0 b 0 0] [0 0 b 0 0] [0 0 0 0 0] [b 0 0 0 0] You should return 2, since bishops 1 and 3 attack each other, as well as bishops 3 and 4. | F68: Not Started | O68: =COUNTA(G68:N68) -> 0
A69: 69 | B69: Easy | C69: Facebook | D69: Given a list of integers, return the largest product that can be made by multiplying any three integ... | E69: Given a list of integers, return the largest product that can be made by multiplying any three integers. For example, if the list is [-10, -10, 5, 2], we should return 500, since that's -10 * -10 * 5. You can assume the list has at least three integers. | F69: Solved | G69: 46017 | J69: 46026 | O69: =COUNTA(G69:N69) -> 2
A70: 70 | B70: Easy | C70: Microsoft | D70: A number is considered perfect if its digits sum up to exactly 10. | E70: A number is considered perfect if its digits sum up to exactly 10. Given a positive integer n, return the n-th perfect number. For example, given 1, you should return 19. Given 2, you should return 28. | F70: Not Started | O70: =COUNTA(G70:N70) -> 0
A71: 71 | B71: Easy | C71: Two Sigma | D71: Using a function rand7() that returns an integer from 1 to 7 (inclusive) with uniform probability, i... | E71: Using a function rand7() that returns an integer from 1 to 7 (inclusive) with uniform probability, implement a function rand5() that returns an integer from 1 to 5 (inclusive). | F71: Not Started | O71: =COUNTA(G71:N71) -> 0
A72: 72 | B72: Hard | C72: Google | D72: In a directed graph, each node is assigned an uppercase letter. | E72: In a directed graph, each node is assigned an uppercase letter. We define a path's value as the number of most frequently-occurring letter along that path. For example, if a path in the graph goes through "ABACA", the value of the path is 3, since there are 3 occurrences of 'A' on the path. Given a graph with n nodes and m directed edges, return the largest value path of the graph. If the largest value is infinite, then return null. The graph is represented with a string and an edge list. The i-th character represents the uppercase letter of the i-th node. Each tuple in the edge list (i, j) means there is a directed edge from the i-th node to the j-th node. Self-edges are possible, as well as multi-edges. For example, the following input graph: ABACA [(0, 1), (0, 2), (2, 3), (3, 4)] Would have maximum value 3 using the path of vertices [0, 2, 3, 4], (A, A, C, A) . The following input graph: A [(0, 0)] Should return null, since we have an infinite loop. | F72: Not Started | O72: =COUNTA(G72:N72) -> 0
A73: 73 | B73: Easy | C73: Google | D73: Given the head of a singly linked list, reverse it in-place. | E73: Given the head of a singly linked list, reverse it in-place. | F73: Solved | G73: 46024 | H73: 46030 | J73: 46023 | K73: 46029 | O73: =COUNTA(G73:N73) -> 4
A74: 74 | B74: Medium | C74: Apple | D74: Suppose you have a multiplication table that is N by N. | E74: Suppose you have a multiplication table that is N by N. That is, a 2D array where the value at the i-th row and j-th column is (i + 1) * (j + 1) (if 0-indexed) or i * j (if 1-indexed). Given integers N and X, write a function that returns the number of times X appears as a value in an N by N multiplication table. For example, given N = 6 and X = 12, you should return 4, since the multiplication table looks like this: | 1 | 2 | 3 | 4 | 5 | 6 | | 2 | 4 | 6 | 8 | 10 | 12 | | 3 | 6 | 9 | 12 | 15 | 18 | | 4 | 8 | 12 | 16 | 20 | 24 | | 5 | 10 | 15 | 20 | 25 | 30 | | 6 | 12 | 18 | 24 | 30 | 36 | And there are 4 12's in the table. | F74: Not Started | O74: =COUNTA(G74:N74) -> 0
A75: 75 | B75: Hard | C75: Microsoft | D75: Given an array of numbers, find the length of the longest increasing subsequence in the array. | E75: Given an array of numbers, find the length of the longest increasing subsequence in the array. The subsequence does not necessarily have to be contiguous. For example, given the array [0, 8, 4, 12, 2, 10, 6, 14, 1, 9, 5, 13, 3, 11, 7, 15], the longest increasing subsequence has length 6: it is 0, 2, 6, 9, 11, 15. | F75: Not Started | O75: =COUNTA(G75:N75) -> 0
A76: 76 | B76: Medium | C76: Google | D76: You are given an N by M 2D matrix of lowercase letters. | E76: You are given an N by M 2D matrix of lowercase letters. Determine the minimum number of columns that can be removed to ensure that each row is ordered from top to bottom lexicographically. That is, the letter at each column is lexicographically later as you go down each row. It does not matter whether each row itself is ordered lexicographically. For example, given the following table: cba daf ghi This is not ordered because of the a in the center. We can remove the second column to make it ordered: ca df gi So your function should return 1, since we only needed to remove 1 column. As another example, given the following table: abcdef Your function should return 0, since the rows are already ordered (there's only one row). As another example, given the following table: zyx wvu tsr Your function should return 3, since we would need to remove all the columns to order it. | F76: Not Started | O76: =COUNTA(G76:N76) -> 0
A77: 77 | B77: Easy | C77: Snapchat | D77: Given a list of possibly overlapping intervals, return a new list of intervals where all overlapping... | E77: Given a list of possibly overlapping intervals, return a new list of intervals where all overlapping intervals have been merged. The input list is not necessarily ordered in any way. For example, given [(1, 3), (5, 8), (4, 10), (20, 25)], you should return [(1, 3), (4, 10), (20, 25)]. | F77: Not Started | O77: =COUNTA(G77:N77) -> 0
A78: 78 | B78: Medium | C78: Google | D78: Given k sorted singly linked lists, write a function to merge all the lists into one sorted singly l... | E78: Given k sorted singly linked lists, write a function to merge all the lists into one sorted singly linked list. | F78: Not Started | O78: =COUNTA(G78:N78) -> 0
A79: 79 | B79: Medium | C79: Facebook | D79: Given an array of integers, write a function to determine whether the array could become non-decreas... | E79: Given an array of integers, write a function to determine whether the array could become non-decreasing by modifying at most 1 element. For example, given the array [10, 5, 7], you should return true, since we can modify the 10 into a 1 to make the array non-decreasing. Given the array [10, 5, 1], you should return false, since we can't modify any one element to get a non-decreasing array. | F79: Not Started | O79: =COUNTA(G79:N79) -> 0
A80: 80 | B80: Easy | C80: Google | D80: Given the root of a binary tree, return a deepest node. | E80: Given the root of a binary tree, return a deepest node. For example, in the following tree, return d. a / \ b c / d | F80: Not Started | O80: =COUNTA(G80:N80) -> 0
A81: 81 | B81: Easy | C81: Yelp | D81: Given a mapping of digits to letters (as in a phone number), and a digit string, return all possible... | E81: Given a mapping of digits to letters (as in a phone number), and a digit string, return all possible letters the number could represent. You can assume each valid number in the mapping is a single digit. For example if {“2”: [“a”, “b”, “c”], 3: [“d”, “e”, “f”], …} then “23” should return [“ad”, “ae”, “af”, “bd”, “be”, “bf”, “cd”, “ce”, “cf"]. | F81: Not Started | O81: =COUNTA(G81:N81) -> 0
A82: 83 | B82: Medium | C82: Google | D82: Invert a binary tree. | E82: Invert a binary tree. For example, given the following tree: a / \ b c / \ / d e f should become: a / \ c b \ / \ f e d | F82: Not Started | O82: =COUNTA(G82:N82) -> 0
A83: 84 | B83: Medium | C83: Amazon | D83: Given a matrix of 1s and 0s, return the number of "islands" in the matrix. | E83: Given a matrix of 1s and 0s, return the number of "islands" in the matrix. A 1 represents land and 0 represents water, so an island is a group of 1s that are neighboring whose perimeter is surrounded by water. For example, this matrix has 4 islands. 1 0 0 0 0 0 0 1 1 0 0 1 1 0 0 0 0 0 0 0 1 1 0 0 1 1 1 0 0 1 | F83: Not Started | O83: =COUNTA(G83:N83) -> 0
A84: 85 | B84: Medium | C84: Facebook | D84: Given three 32-bit integers x, y, and b, return x if b is 1 and y if b is 0, using only mathematical... | E84: Given three 32-bit integers x, y, and b, return x if b is 1 and y if b is 0, using only mathematical or bit operations. You can assume b can only be 1 or 0. | F84: Not Started | O84: =COUNTA(G84:N84) -> 0
A85: 86 | B85: Medium | C85: Google | D85: Given a string of parentheses, write a function to compute the minimum number of parentheses to be r... | E85: Given a string of parentheses, write a function to compute the minimum number of parentheses to be removed to make the string valid (i.e. each open parenthesis is eventually closed). For example, given the string "()())()", you should return 1. Given the string ")(", you should return 2, since we must remove all of them. | F85: Not Started | O85: =COUNTA(G85:N85) -> 0
... A104: 107 | B104: Easy | C104: Microsoft | D104: Print the nodes in a binary tree level-wise. | E104: Print the nodes in a binary tree level-wise. For example, the following should print 1, 2, 3, 4, 5. 1 / \ 2 3 / \ 4 5 | F104: Not Started | O104: =COUNTA(G104:N104) -> 0
A105: 108 | B105: Easy | C105: Google | D105: Given two strings A and B, return whether or not A can be shifted some number of times to get B. | E105: Given two strings A and B, return whether or not A can be shifted some number of times to get B. For example, if A is abcde and B is cdeab, return true. If A is abc and B is acb , return false. | F105: Solved | G105: 46027 | H105: 46027 | I105: 46027 | J105: 46027 | K105: 46028 | L105: 46027 | M105: 46029 | N105: 46028 | O105: =COUNTA(G105:N105) -> 8
A106: 109 | B106: Medium | C106: Cisco | D106: Given an unsigned 8-bit integer, swap its even and odd bits. | E106: Given an unsigned 8-bit integer, swap its even and odd bits. The 1st and 2nd bit should be swapped, the 3rd and 4th bit should be swapped, and so on. For example, 10101010 should be 01010101. 11100010 should be 11010001. Bonus: Can you do this in one line? | F106: Not Started | O106: =COUNTA(G106:N106) -> 0
A107: 110 | B107: Medium | C107: Facebook | D107: Given a binary tree, return all paths from the root to leaves. | E107: Given a binary tree, return all paths from the root to leaves. For example, given the tree: 1 / \ 2 3 / \ 4 5 Return [[1, 2], [1, 3, 4], [1, 3, 5]]. | F107: Not Started | O107: =COUNTA(G107:N107) -> 0
A108: 111 | B108: Hard | C108: Google | D108: Given a word W and a string S, find all starting indices in S which are anagrams of W. | E108: Given a word W and a string S, find all starting indices in S which are anagrams of W. For example, given that W is "ab", and S is "abxaba", return 0, 3, and 4. | F108: Not Started | O108: =COUNTA(G108:N108) -> 0
A109: 112 | B109: Hard | C109: Twitter | D109: Given a binary tree, find the lowest common ancestor (LCA) of two given nodes in the tree. | E109: Given a binary tree, find the lowest common ancestor (LCA) of two given nodes in the tree. Assume that each node in the tree also has a pointer to its parent. According to the definition of LCA on Wikipedia [https://en.wikipedia.org/wiki/Lowest_common_ancestor]: “The lowest common ancestor is defined between two nodes v and w as the lowest node in T that has both v and w as descendants (where we allow a node to be a descendant of itself).” | F109: Not Started | O109: =COUNTA(G109:N109) -> 0
A110: 113 | B110: Medium | C110: Google | D110: Given a string of words delimited by spaces, reverse the words in string. | E110: Given a string of words delimited by spaces, reverse the words in string. For example, given "hello world here", return "here world hello" Follow-up: given a mutable string representation, can you perform this operation in-place? | F110: Not Started | O110: =COUNTA(G110:N110) -> 0
A111: 114 | B111: Hard | C111: Facebook | D111: Given a string and a set of delimiters, reverse the words in the string while maintaining the relati... | E111: Given a string and a set of delimiters, reverse the words in the string while maintaining the relative order of the delimiters. For example, given "hello/world:here", return "here/world:hello" Follow-up: Does your solution work for the following cases: "hello/world:here/", "hello//world:here" | F111: Not Started | O111: =COUNTA(G111:N111) -> 0
A112: 115 | B112: Hard | C112: Google | D112: Given two non-empty binary trees s and t, check whether tree t has exactly the same structure and no... | E112: Given two non-empty binary trees s and t, check whether tree t has exactly the same structure and node values with a subtree of s. A subtree of s is a tree consists of a node in s and all of this node's descendants. The tree s could also be considered as a subtree of itself. | F112: Not Started | O112: =COUNTA(G112:N112) -> 0
A113: 116 | B113: Medium | C113: Jane Street | D113: Generate a finite, but an arbitrarily large binary tree quickly in O(1). | E113: Generate a finite, but an arbitrarily large binary tree quickly in O(1). That is, generate() should return a tree whose size is unbounded but finite. | F113: Not Started | O113: =COUNTA(G113:N113) -> 0
A114: 117 | B114: Easy | C114: Facebook | D114: Given a binary tree, return the level of the tree with minimum sum. | E114: Given a binary tree, return the level of the tree with minimum sum. | F114: Not Started | O114: =COUNTA(G114:N114) -> 0
A115: 118 | B115: Easy | C115: Google | D115: Given a sorted list of integers, square the elements and give the output in sorted order. | E115: Given a sorted list of integers, square the elements and give the output in sorted order. For example, given [-9, -2, 0, 2, 3], return [0, 4, 4, 9, 81]. | F115: Solved | I115: 46015 | J115: 46026 | O115: =COUNTA(G115:N115) -> 2
A116: 119 | B116: Medium | C116: Google | D116: Given a set of closed intervals, find the smallest set of numbers that covers all the intervals. | E116: Given a set of closed intervals, find the smallest set of numbers that covers all the intervals. If there are multiple smallest sets, return any of them. For example, given the intervals [0, 3], [2, 6], [3, 4], [6, 9], one set of numbers that covers all these intervals is {3, 6}. | F116: Not Started | O116: =COUNTA(G116:N116) -> 0
A117: 120 | B117: Medium | C117: Microsoft | D117: Implement the singleton pattern with a twist. | E117: Implement the singleton pattern with a twist. First, instead of storing one instance, store two instances. And in every even call of getInstance(), return the first instance and in every odd call of getInstance(), return the second instance. | F117: Not Started | O117: =COUNTA(G117:N117) -> 0
A118: 121 | B118: Hard | C118: Google | D118: Given a string which we can delete at most k, return whether you can make a palindrome. | E118: Given a string which we can delete at most k, return whether you can make a palindrome. For example, given 'waterrfetawx' and a k of 2, you could delete f and x to get 'waterretaw'. | F118: Not Started | O118: =COUNTA(G118:N118) -> 0
A119: 123 | B119: Hard | C119: LinkedIn | D119: Given a string, return whether it represents a number. | E119: Given a string, return whether it represents a number. Here are the different kinds of numbers: * "10", a positive integer * "-10", a negative integer * "10.1", a positive real number * "-10.1", a negative real number * "1e5", a number in scientific notation And here are examples of non-numbers: * "a" * "x 1" * "a -2" * "-" | F119: Not Started | O119: =COUNTA(G119:N119) -> 0
A120: 124 | B120: Easy | C120: Microsoft | D120: You have n fair coins and you flip them all at the same time. | E120: You have n fair coins and you flip them all at the same time. Any that come up tails you set aside. The ones that come up heads you flip again. How many rounds do you expect to play before only one coin remains? Write a function that, given n, returns the number of rounds you'd expect to play until one coin remains. | F120: Not Started | O120: =COUNTA(G120:N120) -> 0
A121: 125 | B121: Easy | C121: Google | D121: Given the root of a binary search tree, and a target K, return two nodes in the tree whose sum equal... | E121: Given the root of a binary search tree, and a target K, return two nodes in the tree whose sum equals K. For example, given the following tree and K of 20 10 / \ 5 15 / \ 11 15 Return the nodes 5 and 15. | F121: Not Started | O121: =COUNTA(G121:N121) -> 0
A122: 126 | B122: Medium | C122: Facebook | D122: Write a function that rotates a list by k elements. | E122: Write a function that rotates a list by k elements. For example, [1, 2, 3, 4, 5, 6] rotated by two becomes [3, 4, 5, 6, 1, 2]. Try solving this without creating a copy of the list. How many swap or move operations do you need? | F122: Not Started | O122: =COUNTA(G122:N122) -> 0
A123: 127 | B123: Easy | C123: Microsoft | D123: Let's represent an integer in a linked list format by having each node represent a digit in the numb... | E123: Let's represent an integer in a linked list format by having each node represent a digit in the number. The nodes make up the number in reversed order. For example, the following linked list: 1 -> 2 -> 3 -> 4 -> 5 is the number 54321. Given two linked lists in this format, return their sum in the same linked list format. For example, given 9 -> 9 5 -> 2 return 124 (99 + 25) as: 4 -> 2 -> 1 | F123: Not Started | O123: =COUNTA(G123:N123) -> 0
A124: 130 | B124: Medium | C124: Facebook | D124: Given an array of numbers representing the stock prices of a company in chronological order and an i... | E124: Given an array of numbers representing the stock prices of a company in chronological order and an integer k, return the maximum profit you can make from k buys and sells. You must buy the stock before you can sell it, and you must sell the stock before you can buy it again. For example, given k = 2 and the array [5, 2, 4, 0, 1], you should return 3. | F124: Not Started | O124: =COUNTA(G124:N124) -> 0
A125: 133 | B125: Medium | C125: Amazon | D125: Given a node in a binary search tree, return the next bigger element, also known as the inorder succ... | E125: Given a node in a binary search tree, return the next bigger element, also known as the inorder successor. For example, the inorder successor of 22 is 30. 10 / \ 5 30 / \ 22 35 You can assume each node has a parent pointer. | F125: Not Started | O125: =COUNTA(G125:N125) -> 0
A126: 134 | B126: Easy | C126: Facebook | D126: You have a large array with most of the elements as zero. | E126: You have a large array with most of the elements as zero. Use a more space-efficient data structure, SparseArray, that implements the same interface: * init(arr, size): initialize with the original large array and size. * set(i, val): updates index at i with val. * get(i): gets the value at index i. | F126: Not Started | O126: =COUNTA(G126:N126) -> 0
A127: 137 | B127: Medium | C127: Amazon | D127: Implement a bit array. | E127: Implement a bit array. A bit array is a space efficient array that holds a value of 1 or 0 at each index. * init(size): initialize the array with size * set(i, val): updates index at i with val where val is either 1 or 0. * get(i): gets the value at index i. | F127: Not Started | O127: =COUNTA(G127:N127) -> 0
... A144: 158 | B144: Medium | C144: Slack | D144: You are given an N by M matrix of 0s and 1s. | E144: You are given an N by M matrix of 0s and 1s. Starting from the top left corner, how many ways are there to reach the bottom right corner? You can only move right and down. 0 represents an empty space while 1 represents a wall you cannot walk through. For example, given the following matrix: [[0, 0, 1], [0, 0, 1], [1, 0, 0]] Return two, as there are only two ways to get to the bottom right: * Right, down, down, right * Down, right, down, right The top left corner and bottom right corner will always be 0. | F144: Not Started | O144: =COUNTA(G144:N144) -> 0
A145: 159 | B145: Easy | C145: Google | D145: Given a string, return the first recurring character in it, or null if there is no recurring charact... | E145: Given a string, return the first recurring character in it, or null if there is no recurring character. For example, given the string "acbbac", return "b". Given the string "abcdef", return null. | F145: Solved | H145: 46015 | J145: 46022 | K145: 46026 | O145: =COUNTA(G145:N145) -> 3
...

Sheet Summary Stats
A1: DIFFICULTY BREAKDOWN
A2: Difficulty | B2: Total | C2: Solved | D2: Not Started | E2: % Complete
A3: Easy | B3: =COUNTIF(Problems!B:B,"Easy") -> 356 | C3: =COUNTIFS(Problems!B:B,"Easy",Problems!F:F,"Solved") -> 14 | D3: =COUNTIFS(Problems!B:B,"Easy",Problems!F:F,"Not Started") -> 342 | E3: =IF(B3>0,C3/B3,0) -> 0.039325843
A4: Medium | B4: =COUNTIF(Problems!B:B,"Medium") -> 446 | C4: =COUNTIFS(Problems!B:B,"Medium",Problems!F:F,"Solved") -> 1 | D4: =COUNTIFS(Problems!B:B,"Medium",Problems!F:F,"Not Started") -> 445 | E4: =IF(B4>0,C4/B4,0) -> 0.0022421525
A5: Hard | B5: =COUNTIF(Problems!B:B,"Hard") -> 281 | C5: =COUNTIFS(Problems!B:B,"Hard",Problems!F:F,"Solved") -> 0 | D5: =COUNTIFS(Problems!B:B,"Hard",Problems!F:F,"Not Started") -> 281 | E5: =IF(B5>0,C5/B5,0) -> 0
A6: TOTAL | B6: =SUM(B3:B5) -> 1083 | C6: =SUM(C3:C5) -> 15 | D6: =SUM(D3:D5) -> 1068 | E6: =IF(B6>0,C6/B6,0) -> 0.013850416
A9: Language | B9: Total | C9: % Complete
A10: Python | B10: =COUNTA(Problems[Python]) -> 10 | C10: =B10/$B$18 -> 0.25641026
A11: C++ | B11: =COUNTA(Problems[C++]) -> 4 | C11: =B11/$B$18 -> 0.1025641
A12: Rust | B12: =COUNTA(Problems[Rust]) -> 15 | C12: =B12/$B$18 -> 0.38461538
A13: TypeScript | B13: =COUNTA(Problems[TypeScript]) -> 2 | C13: =B13/$B$18 -> 0.051282051
A14: JavaScript | B14: =COUNTA(Problems[JavaScript]) -> 4 | C14: =B14/$B$18 -> 0.1025641
A15: Bash | B15: =COUNTA(Problems[Bash]) -> 1 | C15: =B15/$B$18 -> 0.025641026
A16: C | B16: =COUNTA(Problems[C]) -> 1 | C16: =B16/$B$18 -> 0.025641026
A17: Java | B17: =COUNTA(Problems[Java]) -> 2 | C17: =B17/$B$18 -> 0.051282051
A18: Total | B18: =SUM(B10:B17) -> 39 | C18: =B18/$B$18 -> 1
